MANIFEST.in
README.md
setup.cfg
setup.py
cook/__init__.py
cook/exceptions.py
cook/jobclient.py
cook/utils.py
cook_jobclient.egg-info/PKG-INFO
cook_jobclient.egg-info/SOURCES.txt
cook_jobclient.egg-info/dependency_links.txt
cook_jobclient.egg-info/pbr.json
cook_jobclient.egg-info/requires.txt
cook_jobclient.egg-info/top_level.txt