Metadata-Version: 1.0
Name: cook-jobclient
Version: 1.5.6
Summary: Python library for Cook scheduler REST API
Home-page: https://github.com/m4ce/cook-jobclient-python
Author: Matteo Cerutti
Author-email: matteo.cerutti@hotmail.co.uk
License: Apache License 2.0
Keywords: cook,mesos,jobclient
Platform: UNKNOWN
